{
   "homePageComponents": {
      "telefoneComponents": "Telefones",
      "logoComponents": "logo",
      "ferramentasComponents": {
         "component": "ferramentas",
         "url": "https://uniaotintas.com.br/ferramentas/"
      },
      "ambientesComponents": {
         "component": "//*[@id='main']/div/div[1]/ul/li[2]/a",
         "url": "http://www.coral.com.br/blog/category/ambientes/"
      },
      "dicasComponents": {
         "component": "/html/body/footer/div/div[2]/a",
         "url": "https://uniaotintas.com.br/"
      },
      "contatoUniaoTinta": "/html/body/footer/div/div[2]/a"
   }
}